{
  "name": "bubble",
  "children": [
    {
      "name": "The Tonight Show Starring Jimmy Fallon",
      "description": "",
      "children": [
        {
          "name": "night",
          "address": "",
          "note": ""
        },
        {
          "name": "late",
          "address": ""
        },
        {
          "name": "latenight",
          "address": "",
          "note": ""
        },
        {
          "name": "movie",
          "address": "",
          "note": ""
        },
        {
          "name": "exclusive",
          "address": "",
          "note": ""
        },
        {
          "name": "hashtags",
          "address": "",
          "note": ""
        },
        {
          "name": "twitter",
          "address": "",
          "note": ""
        },
        {
          "name": "web",
          "address": "",
          "note": ""
        },
        {
          "name": "new",
          "address": "",
          "note": ""
        },
        {
          "name": "celebrity",
          "address": "",
          "note": ""
        }
      ]
    },
    {
      "name": "CollegeHumor",
      "description": "",
      "children": [
        {
          "name": "comedy",
          "address": "",
          "note": ""
        },
        {
          "name": "sketch",
          "address": "",
          "note": ""
        },
        {
          "name": "chtv",
          "address": ""
        },
        {
          "name": "amir",
          "address": ""
        },
        {
          "name": "jake",
          "address": ""
        },
        {
          "name": "humor",
          "address": ""
        },
        {
          "name": "working",
          "address": ""
        },
        {
          "name": "hardly",
          "address": ""
        },
        {
          "name": "hilarious",
          "address": ""
        },
        {
          "name": "office",
          "address": ""
        }
      ]
    },
    {
      "name": "Jimmy Kimmel Live",
      "description": "",
      "children": [
        {
          "name": "colbert",
          "address": ""
        },
        {
          "name": "fallon",
          "address": ""
        },
        {
          "name": "sketch",
          "address": ""
        },
        {
          "name": "stephen",
          "address": ""
        },
        {
          "name": "music",
          "address": ""
        },
        {
          "name": "video",
          "address": ""
        },
        {
          "name": "stand",
          "address": ""
        },
        {
          "name": "variety",
          "address": ""
        },
        {
          "name": "humor",
          "address": ""
        },
        {
          "name": "actor",
          "address": ""
        }
      ]
    },
    {
      "name": "Just For Laughs Gags",
      "description": "",
      "children": [
        {
          "name": "pranks",
          "address": ""
        },
        {
          "name": "humour",
          "address": ""
        },
        {
          "name": "laugh",
          "address": ""
        },
        {
          "name": "justforlaughs",
          "address": ""
        },
        {
          "name": "funniest",
          "address": ""
        },
        {
          "name": "laughing",
          "address": ""
        },
        {
          "name": "jflgags",
          "address": ""
        },
        {
          "name": "comic",
          "address": ""
        },
        {
          "name": "justforlaughstv",
          "address": ""
        },
        {
          "name": "stupid",
          "address": ""
        }
      ]
    },
    {
      "name": "Comedy Central",
      "description": "",
      "children": [
        {
          "name": "midnight",
          "address": ""
        },
        {
          "name": "peele",
          "address": ""
        },
        {
          "name": "key",
          "address": ""
        },
        {
          "name": "daily",
          "address": ""
        },
        {
          "name": "nightly",
          "address": ""
        },
        {
          "name": "larry",
          "address": ""
        },
        {
          "name": "kroll",
          "address": ""
        },
        {
          "name": "chris",
          "address": ""
        },
        {
          "name": "wilmore",
          "address": ""
        },
        {
          "name": "amy",
          "address": ""
        }
      ]
    }
  ]
}